{
  "$schema": "http://json-schema.org/schema#",
  "$id": "https://metasys-server.github.io/schemas/v1/enums/airconditionVentilationEnumSet.schema.json",
  "title": "airconditionVentilationEnumSet",
  "description": "Air Conditioning Ventilation",
  "oneOf": [
    {
      "enum": [
        0,
        "0"
      ],
      "description": "Air Conditioning"
    },
    {
      "enum": [
        1,
        "1"
      ],
      "description": "Ventilation"
    },
    {
      "enum": [
        2,
        "2"
      ],
      "description": "Hold"
    },
    {
      "type": "null"
    }
  ]
}