{
  "$schema": "http://json-schema.org/schema#",
  "$id": "https://metasys-server.github.io/schemas/v1/enums/clockwiseEnumSet.schema.json",
  "title": "clockwiseEnumSet",
  "description": "Clockwise Counterclockwise",
  "oneOf": [
    {
      "enum": [
        0,
        "clockwise"
      ],
      "description": "Clockwise"
    },
    {
      "enum": [
        1,
        "counterClockwise"
      ],
      "description": "Counterclockwise"
    },
    {
      "enum": [
        2,
        "clockwiseHold"
      ],
      "description": "Hold"
    },
    {
      "type": "null"
    }
  ]
}