{
  "$schema": "http://json-schema.org/schema#",
  "$id": "https://metasys-server.github.io/schemas/v1/enums/elementNameEnumSet.schema.json",
  "title": "elementNameEnumSet",
  "description": "Element Name",
  "oneOf": [
    {
      "enum": [
        0,
        "major"
      ],
      "description": "Major"
    },
    {
      "enum": [
        1,
        "minor"
      ],
      "description": "Minor"
    },
    {
      "enum": [
        2,
        "objectName"
      ],
      "description": "Object Name"
    },
    {
      "enum": [
        3,
        "functionalName"
      ],
      "description": "Functional Name"
    },
    {
      "enum": [
        4,
        "referenceName"
      ],
      "description": "Reference Name"
    },
    {
      "enum": [
        5,
        "instance"
      ],
      "description": "Instance"
    },
    {
      "enum": [
        6,
        "index"
      ],
      "description": "Index"
    },
    {
      "enum": [
        7,
        "childOid"
      ],
      "description": "Child OID"
    },
    {
      "enum": [
        8,
        "isReference"
      ],
      "description": "Is Reference"
    },
    {
      "enum": [
        9,
        "internal"
      ],
      "description": "Internal"
    },
    {
      "enum": [
        10,
        "label"
      ],
      "description": "Label"
    },
    {
      "enum": [
        11,
        "device"
      ],
      "description": "Device"
    },
    {
      "enum": [
        12,
        "address"
      ],
      "description": "Address"
    },
    {
      "enum": [
        13,
        "element"
      ],
      "description": "Element"
    },
    {
      "enum": [
        14,
        "time"
      ],
      "description": "Time"
    },
    {
      "enum": [
        15,
        "value"
      ],
      "description": "Value"
    },
    {
      "enum": [
        16,
        "classId"
      ],
      "description": "Class ID"
    },
    {
      "enum": [
        17,
        "className"
      ],
      "description": "Class Name"
    },
    {
      "enum": [
        18,
        "version"
      ],
      "description": "Version"
    },
    {
      "enum": [
        19,
        "commandId"
      ],
      "description": "Command ID"
    },
    {
      "enum": [
        20,
        "priority"
      ],
      "description": "Priority"
    },
    {
      "enum": [
        21,
        "runningDelay"
      ],
      "description": "Running Delay"
    },
    {
      "enum": [
        22,
        "delay"
      ],
      "description": "Delay"
    },
    {
      "enum": [
        23,
        "parameters"
      ],
      "description": "Parameters"
    },
    {
      "enum": [
        24,
        "bindCount"
      ],
      "description": "Bind Count"
    },
    {
      "enum": [
        25,
        "periodStartDate"
      ],
      "description": "Period Start Date"
    },
    {
      "enum": [
        26,
        "periodStartTime"
      ],
      "description": "Period Start Time"
    },
    {
      "enum": [
        27,
        "periodEndDate"
      ],
      "description": "Period End Date"
    },
    {
      "enum": [
        28,
        "periodEndTime"
      ],
      "description": "Period End Time"
    },
    {
      "enum": [
        29,
        "consumption"
      ],
      "description": "Consumption"
    },
    {
      "enum": [
        30,
        "dataUnreliable"
      ],
      "description": "Data Unreliable"
    },
    {
      "enum": [
        31,
        "demandPeak"
      ],
      "description": "Demand Peak"
    },
    {
      "enum": [
        32,
        "demandPeakDate"
      ],
      "description": "Demand Peak Date"
    },
    {
      "enum": [
        33,
        "demandPeakTime"
      ],
      "description": "Demand Peak Time"
    },
    {
      "enum": [
        34,
        "uncDemandPeak"
      ],
      "description": "Unc Demand Peak"
    },
    {
      "enum": [
        35,
        "uncDemandPeakDate"
      ],
      "description": "Unc Demand Peak Date"
    },
    {
      "enum": [
        36,
        "uncDemandPeakTime"
      ],
      "description": "Unc Demand Peak Time"
    },
    {
      "enum": [
        37,
        "loadOid"
      ],
      "description": "Load OID"
    },
    {
      "enum": [
        38,
        "loadCommandIid"
      ],
      "description": "Load Command IID"
    },
    {
      "enum": [
        39,
        "shedRate"
      ],
      "description": "Shed Rate"
    },
    {
      "enum": [
        40,
        "amountShed"
      ],
      "description": "Amount Shed"
    },
    {
      "enum": [
        41,
        "relation"
      ],
      "description": "Relation"
    },
    {
      "enum": [
        42,
        "differential"
      ],
      "description": "Differential"
    },
    {
      "enum": [
        43,
        "difference"
      ],
      "description": "Difference"
    },
    {
      "enum": [
        44,
        "result"
      ],
      "description": "Result"
    },
    {
      "enum": [
        45,
        "reliable"
      ],
      "description": "Reliable"
    },
    {
      "enum": [
        46,
        "consumpUnreliable"
      ],
      "description": "Consump Unreliable"
    },
    {
      "enum": [
        47,
        "peakUnreliable"
      ],
      "description": "Peak Unreliable"
    },
    {
      "enum": [
        48,
        "battery"
      ],
      "description": "Battery"
    },
    {
      "enum": [
        49,
        "startupCode"
      ],
      "description": "Startup Code"
    },
    {
      "enum": [
        50,
        "bootCode"
      ],
      "description": "Boot Code"
    },
    {
      "enum": [
        51,
        "mainCode"
      ],
      "description": "Main Code"
    },
    {
      "enum": [
        52,
        "configuration"
      ],
      "description": "Configuration"
    },
    {
      "enum": [
        53,
        "n2Port"
      ],
      "description": "N2 Port"
    },
    {
      "enum": [
        54,
        "port1"
      ],
      "description": "Port 1"
    },
    {
      "enum": [
        55,
        "port2"
      ],
      "description": "Port 2"
    },
    {
      "enum": [
        56,
        "port3"
      ],
      "description": "Port 3"
    },
    {
      "enum": [
        57,
        "ethernet"
      ],
      "description": "Ethernet"
    },
    {
      "enum": [
        58,
        "dictionary"
      ],
      "description": "Dictionary"
    },
    {
      "enum": [
        59,
        "pioSyncFld"
      ],
      "description": "Percent IO Sync"
    },
    {
      "enum": [
        60,
        "pioTypeFld"
      ],
      "description": "Percent IO Type"
    },
    {
      "enum": [
        61,
        "pioValueFld"
      ],
      "description": "Percent IO Value"
    },
    {
      "enum": [
        62,
        "pioOvrdStateFld"
      ],
      "description": "Percnt IO Ovrd State"
    },
    {
      "enum": [
        63,
        "pioOvrdValueFld"
      ],
      "description": "Pecnt IO Ovrd Value"
    },
    {
      "enum": [
        64,
        "hvacOvrdStateFld"
      ],
      "description": "HVAC Override State"
    },
    {
      "enum": [
        65,
        "hvacOvrdPercentFld"
      ],
      "description": "HVAC Ovrd Percent"
    },
    {
      "enum": [
        66,
        "hvacOvrdFlowFld"
      ],
      "description": "HVAC Override Flow"
    },
    {
      "enum": [
        67,
        "tempSetptOccupiedCoolFld"
      ],
      "description": "Occupied Cooling"
    },
    {
      "enum": [
        68,
        "tempSetptStandbyCoolFld"
      ],
      "description": "Standby Cooling"
    },
    {
      "enum": [
        69,
        "tempSetptUnoccupiedCoolFld"
      ],
      "description": "Unoccupied Cooling"
    },
    {
      "enum": [
        70,
        "tempSetptOccupiedHeatFld"
      ],
      "description": "Occupied Heating"
    },
    {
      "enum": [
        71,
        "tempSetptStandbyHeatFld"
      ],
      "description": "Standby Heating"
    },
    {
      "enum": [
        72,
        "tempSetptUnoccupiedHeatFld"
      ],
      "description": "Unoccupied Heating"
    },
    {
      "enum": [
        73,
        "todEvntCurStateFld"
      ],
      "description": "Current State"
    },
    {
      "enum": [
        74,
        "todEvntNxtStateFld"
      ],
      "description": "TOD Next State"
    },
    {
      "enum": [
        75,
        "todEvntTimeToStateFld"
      ],
      "description": "Time To State"
    },
    {
      "enum": [
        76,
        "switchValueFld"
      ],
      "description": "Switch Value"
    },
    {
      "enum": [
        77,
        "switchStateFld"
      ],
      "description": "Switch State"
    },
    {
      "enum": [
        78,
        "modeFld"
      ],
      "description": "Unit Mode"
    },
    {
      "enum": [
        79,
        "primaryHeatFld"
      ],
      "description": "Primary Heat"
    },
    {
      "enum": [
        80,
        "secondaryHeatFld"
      ],
      "description": "Secondary Heat"
    },
    {
      "enum": [
        81,
        "coolOutputFld"
      ],
      "description": "Cool Output"
    },
    {
      "enum": [
        82,
        "econOutputFld"
      ],
      "description": "Econ Output"
    },
    {
      "enum": [
        83,
        "fanOutputFld"
      ],
      "description": "Fan Output"
    },
    {
      "enum": [
        84,
        "inAlarmFld"
      ],
      "description": "In Alarm"
    },
    {
      "enum": [
        85,
        "ipAddress"
      ],
      "description": "IP Address"
    },
    {
      "enum": [
        86,
        "ipMask"
      ],
      "description": "IP Broadcast Mask"
    },
    {
      "enum": [
        87,
        "presentValue"
      ],
      "description": "Present Value"
    },
    {
      "enum": [
        88,
        "extPresentValue"
      ],
      "description": "Ext Present Value"
    },
    {
      "enum": [
        89,
        "transitionIndex"
      ],
      "description": "Transition Index"
    },
    {
      "enum": [
        90,
        "transitionTime"
      ],
      "description": "Transition Time"
    },
    {
      "enum": [
        91,
        "transitionDate"
      ],
      "description": "Transition Date"
    },
    {
      "enum": [
        92,
        "maxcounts"
      ],
      "description": "Max Counts"
    },
    {
      "enum": [
        93,
        "mincounts"
      ],
      "description": "Min Counts"
    },
    {
      "enum": [
        94,
        "refmax"
      ],
      "description": "Ref Max"
    },
    {
      "enum": [
        95,
        "refmin"
      ],
      "description": "Ref Min"
    },
    {
      "enum": [
        96,
        "validDays"
      ],
      "description": "Valid Days"
    },
    {
      "enum": [
        97,
        "fromTime"
      ],
      "description": "From Time"
    },
    {
      "enum": [
        98,
        "toTime"
      ],
      "description": "To Time"
    },
    {
      "enum": [
        99,
        "objId"
      ],
      "description": "Object ID"
    },
    {
      "enum": [
        100,
        "recNbr"
      ],
      "description": "Address-Net Nbr"
    },
    {
      "enum": [
        101,
        "recIp"
      ],
      "description": "Address-IP"
    },
    {
      "enum": [
        102,
        "recUdp"
      ],
      "description": "Address-UDP Port"
    },
    {
      "enum": [
        103,
        "procId"
      ],
      "description": "Process Identifier"
    },
    {
      "enum": [
        104,
        "confNotif"
      ],
      "description": "Confirmed Notif"
    },
    {
      "enum": [
        105,
        "transitions"
      ],
      "description": "Transitions"
    },
    {
      "enum": [
        106,
        "recChoice"
      ],
      "description": "Recipient Choice"
    },
    {
      "enum": [
        107,
        "specifyDevice"
      ],
      "description": "Specify Device"
    },
    {
      "enum": [
        108,
        "attribute"
      ],
      "description": "Attribute"
    },
    {
      "enum": [
        109,
        "specifyArrayIndex"
      ],
      "description": "Specify Array Index"
    },
    {
      "enum": [
        110,
        "specifyPriority"
      ],
      "description": "Specify Priority"
    },
    {
      "enum": [
        111,
        "specifyDelay"
      ],
      "description": "Specify Delay"
    },
    {
      "enum": [
        112,
        "quitOnFailure"
      ],
      "description": "Quit on Failure"
    },
    {
      "enum": [
        113,
        "writeSucessful"
      ],
      "description": "Write Sucessful"
    },
    {
      "enum": [
        114,
        "vctFileName"
      ],
      "description": "VCT File Name"
    },
    {
      "enum": [
        115,
        "interface"
      ],
      "description": "Interface"
    },
    {
      "enum": [
        116,
        "netPointType"
      ],
      "description": "Net Point Type"
    },
    {
      "enum": [
        117,
        "netPointAddress"
      ],
      "description": "Net Point Address"
    },
    {
      "enum": [
        118,
        "units"
      ],
      "description": "Units"
    },
    {
      "enum": [
        119,
        "displayPrecision"
      ],
      "description": "Display Precision"
    },
    {
      "enum": [
        120,
        "status"
      ],
      "description": "Status"
    },
    {
      "enum": [
        121,
        "hostName"
      ],
      "description": "Host Name"
    },
    {
      "enum": [
        122,
        "changeOfBitstring"
      ],
      "description": "Change of Bitstring"
    },
    {
      "enum": [
        123,
        "changeOfState"
      ],
      "description": "Change of State"
    },
    {
      "enum": [
        124,
        "changeOfValue"
      ],
      "description": "Change of Value"
    },
    {
      "enum": [
        125,
        "commandFailure"
      ],
      "description": "Command Failure"
    },
    {
      "enum": [
        126,
        "floatingLimit"
      ],
      "description": "Floating Limit"
    },
    {
      "enum": [
        127,
        "outOfRange"
      ],
      "description": "Out of Range"
    },
    {
      "enum": [
        128,
        "bufferReady"
      ],
      "description": "Buffer Ready"
    },
    {
      "enum": [
        129,
        "changeOfLifeSafety"
      ],
      "description": "Change of Life Safet"
    },
    {
      "enum": [
        130,
        "timeDelay"
      ],
      "description": "Time Delay"
    },
    {
      "enum": [
        131,
        "bitmask"
      ],
      "description": "Bitmask"
    },
    {
      "enum": [
        132,
        "bitstringValues"
      ],
      "description": "Bitstring Values"
    },
    {
      "enum": [
        133,
        "listOfValues"
      ],
      "description": "List of Values"
    },
    {
      "enum": [
        134,
        "booleanValue"
      ],
      "description": "Boolean Value"
    },
    {
      "enum": [
        135,
        "binaryValue"
      ],
      "description": "Binary Value"
    },
    {
      "enum": [
        136,
        "eventType"
      ],
      "description": "Event Type"
    },
    {
      "enum": [
        137,
        "polarity"
      ],
      "description": "Polarity"
    },
    {
      "enum": [
        138,
        "programChange"
      ],
      "description": "Program Change"
    },
    {
      "enum": [
        139,
        "programState"
      ],
      "description": "Program State"
    },
    {
      "enum": [
        140,
        "reasonForHalt"
      ],
      "description": "Reason for Halt"
    },
    {
      "enum": [
        141,
        "reliability"
      ],
      "description": "Reliability"
    },
    {
      "enum": [
        142,
        "state"
      ],
      "description": "State"
    },
    {
      "enum": [
        143,
        "systemStatus"
      ],
      "description": "System Status"
    },
    {
      "enum": [
        144,
        "unsignedValue"
      ],
      "description": "Unsigned Value"
    },
    {
      "enum": [
        145,
        "lifeSafetyMode"
      ],
      "description": "Life Safety Mode"
    },
    {
      "enum": [
        146,
        "lifeSafetyState"
      ],
      "description": "Life Safety State"
    },
    {
      "enum": [
        147,
        "covIncrement"
      ],
      "description": "COV Increment"
    },
    {
      "enum": [
        148,
        "feedbackRef"
      ],
      "description": "Feedback Reference"
    },
    {
      "enum": [
        149,
        "propertyId"
      ],
      "description": "Property ID"
    },
    {
      "enum": [
        150,
        "arrayIndex"
      ],
      "description": "Array Index"
    },
    {
      "enum": [
        151,
        "deviceId"
      ],
      "description": "Device ID"
    },
    {
      "enum": [
        152,
        "setpointRef"
      ],
      "description": "Setpoint Reference"
    },
    {
      "enum": [
        153,
        "lowDiffLimit"
      ],
      "description": "Low Diff Limit"
    },
    {
      "enum": [
        154,
        "highDiffLimit"
      ],
      "description": "High Diff Limit"
    },
    {
      "enum": [
        155,
        "deadband"
      ],
      "description": "Deadband"
    },
    {
      "enum": [
        156,
        "lowLimit"
      ],
      "description": "Low Limit"
    },
    {
      "enum": [
        157,
        "highLimit"
      ],
      "description": "High Limit"
    },
    {
      "enum": [
        158,
        "notifThreshold"
      ],
      "description": "Notif Threshold"
    },
    {
      "enum": [
        159,
        "prevNotifCount"
      ],
      "description": "Previous Notif Count"
    },
    {
      "enum": [
        160,
        "lifesftyAlmValsList"
      ],
      "description": "LifeSafety Alrm Vals"
    },
    {
      "enum": [
        161,
        "almValsList"
      ],
      "description": "Alarm Values"
    },
    {
      "enum": [
        162,
        "modeRef"
      ],
      "description": "Mode Reference"
    },
    {
      "enum": [
        163,
        "date"
      ],
      "description": "Date"
    },
    {
      "enum": [
        164,
        "taskid"
      ],
      "description": "Task ID"
    },
    {
      "enum": [
        165,
        "error"
      ],
      "description": "Error"
    },
    {
      "enum": [
        166,
        "trendAltRef"
      ],
      "description": "Alternate Reference"
    },
    {
      "enum": [
        167,
        "trendAggFunc"
      ],
      "description": "Aggregate Function"
    },
    {
      "enum": [
        168,
        "trendAggInt"
      ],
      "description": "Aggregate Interval"
    },
    {
      "enum": [
        169,
        "trendPlotMethod"
      ],
      "description": "Plotting Method"
    },
    {
      "enum": [
        170,
        "connUsing"
      ],
      "description": "Connect Using"
    },
    {
      "enum": [
        171,
        "phoneNum"
      ],
      "description": "Access Number"
    },
    {
      "enum": [
        172,
        "redialAttempts"
      ],
      "description": "Redial Attempts"
    },
    {
      "enum": [
        173,
        "redialTime"
      ],
      "description": "Time Between Redial Attempts"
    },
    {
      "enum": [
        174,
        "hangUpTime"
      ],
      "description": "Idle Time Before Hanging Up"
    },
    {
      "enum": [
        175,
        "redialIfDropped"
      ],
      "description": "Redial If Line Is Dropped"
    },
    {
      "enum": [
        176,
        "enableInternetConn"
      ],
      "description": "Enable Internet Connection Sharing"
    },
    {
      "enum": [
        177,
        "enableDhcp"
      ],
      "description": "Enable DHCP"
    },
    {
      "enum": [
        178,
        "obtainDnsAuto"
      ],
      "description": "Obtain DNS Address Automatically"
    },
    {
      "enum": [
        179,
        "dnsAddrs"
      ],
      "description": "DNS Server IP Addresses"
    },
    {
      "enum": [
        180,
        "ispUsername"
      ],
      "description": "ISP Username"
    },
    {
      "enum": [
        181,
        "ispPassword"
      ],
      "description": "ISP Password"
    },
    {
      "enum": [
        182,
        "enabled"
      ],
      "description": "Enabled"
    },
    {
      "enum": [
        183,
        "allowIncomingConns"
      ],
      "description": "Allow Incoming Connections"
    },
    {
      "enum": [
        184,
        "baudRate"
      ],
      "description": "Baud Rate"
    },
    {
      "enum": [
        185,
        "maxBaudRate"
      ],
      "description": "Maximum Baud Rate"
    },
    {
      "enum": [
        186,
        "waitForDial"
      ],
      "description": "Wait For Dial Tone Before Dialing"
    },
    {
      "enum": [
        187,
        "modemInitStr"
      ],
      "description": "Extra Initialization Commands"
    },
    {
      "enum": [
        188,
        "item"
      ],
      "description": "Item"
    },
    {
      "enum": [
        189,
        "operator"
      ],
      "description": "Operator"
    },
    {
      "enum": [
        190,
        "emailAddr"
      ],
      "description": "Email Address"
    },
    {
      "enum": [
        191,
        "subject"
      ],
      "description": "Subject"
    },
    {
      "enum": [
        192,
        "retries"
      ],
      "description": "Retries"
    },
    {
      "enum": [
        193,
        "filters"
      ],
      "description": "Event Filters"
    },
    {
      "enum": [
        194,
        "format"
      ],
      "description": "Format"
    },
    {
      "enum": [
        195,
        "userIdNum"
      ],
      "description": "Pager Phone Number"
    },
    {
      "enum": [
        196,
        "maxChars"
      ],
      "description": "Max Characters"
    },
    {
      "enum": [
        197,
        "communityName"
      ],
      "description": "Trap Community Name"
    },
    {
      "enum": [
        198,
        "destPortNum"
      ],
      "description": "Destination Port Number"
    },
    {
      "enum": [
        199,
        "toOffnormal"
      ],
      "description": "To Off Normal"
    },
    {
      "enum": [
        200,
        "toFault"
      ],
      "description": "To Fault"
    },
    {
      "enum": [
        201,
        "toNormal"
      ],
      "description": "To Normal"
    },
    {
      "enum": [
        202,
        "path"
      ],
      "description": "Path"
    },
    {
      "enum": [
        203,
        "printer"
      ],
      "description": "Printer"
    },
    {
      "enum": [
        204,
        "recipient"
      ],
      "description": "Recipient"
    },
    {
      "enum": [
        205,
        "fontface"
      ],
      "description": "Font Face"
    },
    {
      "enum": [
        206,
        "fontsize"
      ],
      "description": "Font Size"
    },
    {
      "enum": [
        207,
        "orientation"
      ],
      "description": "Orientation"
    },
    {
      "enum": [
        208,
        "timeout"
      ],
      "description": "Timeout"
    },
    {
      "enum": [
        209,
        "elementReference"
      ],
      "description": "Element Reference"
    },
    {
      "enum": [
        210,
        "type"
      ],
      "description": "Type"
    },
    {
      "enum": [
        211,
        "category"
      ],
      "description": "Category"
    },
    {
      "enum": [
        212,
        "unitsOrEnumSet"
      ],
      "description": "Units Or Enum Set"
    },
    {
      "enum": [
        213,
        "commands"
      ],
      "description": "Commands"
    },
    {
      "enum": [
        214,
        "override"
      ],
      "description": "Override"
    },
    {
      "enum": [
        215,
        "adjust"
      ],
      "description": "Adjust"
    },
    {
      "enum": [
        216,
        "minValue"
      ],
      "description": "Min Value"
    },
    {
      "enum": [
        217,
        "maxValue"
      ],
      "description": "Max Value"
    },
    {
      "enum": [
        218,
        "fieldEngUnits"
      ],
      "description": "Field Engineering Units"
    },
    {
      "enum": [
        219,
        "refFlag"
      ],
      "description": "Ref Flag"
    },
    {
      "enum": [
        220,
        "expFlag"
      ],
      "description": "Exp Flag"
    },
    {
      "enum": [
        221,
        "references"
      ],
      "description": "References"
    },
    {
      "enum": [
        222,
        "lineout"
      ],
      "description": "Line Out"
    },
    {
      "enum": [
        223,
        "printingPriority"
      ],
      "description": "Printing Priority Threshold"
    },
    {
      "enum": [
        224,
        "sourceblock"
      ],
      "description": "Source Block"
    },
    {
      "enum": [
        225,
        "sourceattr"
      ],
      "description": "Source Attribute"
    },
    {
      "enum": [
        226,
        "destblock"
      ],
      "description": "Destination Block"
    },
    {
      "enum": [
        227,
        "destattr"
      ],
      "description": "Destination Attribute"
    },
    {
      "enum": [
        228,
        "object"
      ],
      "description": "Object"
    },
    {
      "enum": [
        229,
        "attributes"
      ],
      "description": "Attributes"
    },
    {
      "enum": [
        230,
        "writeStatus"
      ],
      "description": "Write Status"
    },
    {
      "enum": [
        231,
        "dataType"
      ],
      "description": "Data Type"
    },
    {
      "enum": [
        232,
        "blocks"
      ],
      "description": "Blocks"
    },
    {
      "enum": [
        233,
        "outputEnumSet"
      ],
      "description": "Output Enum Set"
    },
    {
      "enum": [
        234,
        "columnHeading"
      ],
      "description": "Column Heading"
    },
    {
      "enum": [
        235,
        "columnValue"
      ],
      "description": "Column Value"
    },
    {
      "enum": [
        236,
        "stateEnumSet"
      ],
      "description": "State Enum Set"
    },
    {
      "enum": [
        237,
        "rowValue"
      ],
      "description": "Row Value"
    },
    {
      "enum": [
        238,
        "mapped"
      ],
      "description": "Mapped"
    },
    {
      "enum": [
        239,
        "maxMaster"
      ],
      "description": "Max Master"
    },
    {
      "enum": [
        240,
        "maxInfoFrames"
      ],
      "description": "Max Info Frames"
    },
    {
      "enum": [
        241,
        "portStatus"
      ],
      "description": "Port Status"
    },
    {
      "enum": [
        242,
        "codeState"
      ],
      "description": "Code State"
    },
    {
      "enum": [
        243,
        "xPosition"
      ],
      "description": "X Position"
    },
    {
      "enum": [
        244,
        "yPosition"
      ],
      "description": "Y Position"
    },
    {
      "enum": [
        245,
        "continuationFlag"
      ],
      "description": "Continuation Flag"
    },
    {
      "enum": [
        246,
        "continuationText"
      ],
      "description": "Continuation Text"
    },
    {
      "enum": [
        247,
        "connections"
      ],
      "description": "Connections"
    },
    {
      "enum": [
        248,
        "slot"
      ],
      "description": "Slot"
    },
    {
      "enum": [
        249,
        "remoteDeviceReference"
      ],
      "description": "Device Reference"
    },
    {
      "enum": [
        250,
        "slota"
      ],
      "description": "Slot A"
    },
    {
      "enum": [
        251,
        "slotb"
      ],
      "description": "Slot B"
    },
    {
      "enum": [
        252,
        "timeConstant"
      ],
      "description": "Time Constant"
    },
    {
      "enum": [
        253,
        "deadtime"
      ],
      "description": "Deadtime"
    },
    {
      "enum": [
        254,
        "processRange"
      ],
      "description": "Process Range"
    },
    {
      "enum": [
        255,
        "effortMean"
      ],
      "description": "Effort Mean"
    },
    {
      "enum": [
        256,
        "effortStdDev"
      ],
      "description": "Effort Std Dev"
    },
    {
      "enum": [
        257,
        "errorMean"
      ],
      "description": "Error Mean"
    },
    {
      "enum": [
        258,
        "errorStdDev"
      ],
      "description": "Error Std Dev"
    },
    {
      "enum": [
        259,
        "errorMeanStaged"
      ],
      "description": "Error Mean Staged"
    },
    {
      "enum": [
        260,
        "errorStdDevStaged"
      ],
      "description": "Error Std Dev Staged"
    },
    {
      "enum": [
        261,
        "accessGroupId"
      ],
      "description": "Access Group ID"
    },
    {
      "enum": [
        262,
        "pagerDatabits"
      ],
      "description": "Databits"
    },
    {
      "enum": [
        263,
        "pagerParity"
      ],
      "description": "Parity"
    },
    {
      "enum": [
        264,
        "pagerStopbits"
      ],
      "description": "Stopbits"
    },
    {
      "enum": [
        265,
        "vendorId"
      ],
      "description": "Vendor ID"
    },
    {
      "enum": [
        266,
        "iagType"
      ],
      "description": "IAG Type"
    },
    {
      "enum": [
        267,
        "inputLabel"
      ],
      "description": "Input Label"
    },
    {
      "enum": [
        268,
        "inputType"
      ],
      "description": "Input Type"
    },
    {
      "enum": [
        269,
        "transitionMapping"
      ],
      "description": "Transition Mapping"
    },
    {
      "enum": [
        270,
        "operatora"
      ],
      "description": "Operator A"
    },
    {
      "enum": [
        271,
        "operand"
      ],
      "description": "Operand"
    },
    {
      "enum": [
        272,
        "operatorbType"
      ],
      "description": "Operator B Type"
    },
    {
      "enum": [
        273,
        "operatorbValue"
      ],
      "description": "Operator B Value"
    },
    {
      "enum": [
        274,
        "stateName"
      ],
      "description": "State Name"
    },
    {
      "enum": [
        275,
        "stateEnum"
      ],
      "description": "State Enum"
    },
    {
      "enum": [
        276,
        "stateValue"
      ],
      "description": "State Value"
    },
    {
      "enum": [
        277,
        "stateMask"
      ],
      "description": "State Mask"
    },
    {
      "enum": [
        278,
        "stateCompare"
      ],
      "description": "State Compare"
    },
    {
      "enum": [
        279,
        "transitionMask"
      ],
      "description": "Transition Mask"
    },
    {
      "enum": [
        280,
        "transitionCompare"
      ],
      "description": "Transition Compare"
    },
    {
      "enum": [
        281,
        "nextState"
      ],
      "description": "Next State"
    },
    {
      "enum": [
        282,
        "timerDuration"
      ],
      "description": "Timer Duration"
    },
    {
      "enum": [
        283,
        "inputAttributeNumber"
      ],
      "description": "Input Attribute Number"
    },
    {
      "enum": [
        284,
        "teLocation"
      ],
      "description": "TE Location"
    },
    {
      "enum": [
        285,
        "teHandled"
      ],
      "description": "TE Handled"
    },
    {
      "enum": [
        286,
        "pinUse"
      ],
      "description": "PIN Use"
    },
    {
      "enum": [
        287,
        "pin"
      ],
      "description": "PIN"
    },
    {
      "enum": [
        288,
        "aiAttrrefType"
      ],
      "description": "AI Attr Ref Type"
    },
    {
      "enum": [
        289,
        "aiPreviousEventTimeType"
      ],
      "description": "AI Previous Event Time Type"
    },
    {
      "enum": [
        290,
        "aiCurrentEventTimeType"
      ],
      "description": "AI Current Event Time Type"
    },
    {
      "enum": [
        291,
        "aiPreviousStateType"
      ],
      "description": "AI Previous State Type"
    },
    {
      "enum": [
        292,
        "confirmed"
      ],
      "description": "Confirmed"
    },
    {
      "enum": [
        293,
        "remaining"
      ],
      "description": "Remaining"
    },
    {
      "enum": [
        294,
        "eol"
      ],
      "description": "EOL"
    },
    {
      "enum": [
        295,
        "model"
      ],
      "description": "Model"
    },
    {
      "enum": [
        296,
        "bits"
      ],
      "description": "Bits"
    },
    {
      "enum": [
        297,
        "firstBit"
      ],
      "description": "First Bit"
    },
    {
      "enum": [
        298,
        "groupType"
      ],
      "description": "Group Type"
    },
    {
      "enum": [
        299,
        "groupId"
      ],
      "description": "Group ID"
    },
    {
      "enum": [
        300,
        "scheduleObject"
      ],
      "description": "Schedule Object"
    },
    {
      "enum": [
        301,
        "startDate"
      ],
      "description": "Start Date"
    },
    {
      "enum": [
        302,
        "startTime"
      ],
      "description": "Start Time"
    },
    {
      "enum": [
        303,
        "endDate"
      ],
      "description": "End Date"
    },
    {
      "enum": [
        304,
        "endTime"
      ],
      "description": "End Time"
    },
    {
      "enum": [
        305,
        "purpose"
      ],
      "description": "Purpose"
    },
    {
      "enum": [
        306,
        "mask"
      ],
      "description": "Mask"
    },
    {
      "enum": [
        307,
        "floorNumber"
      ],
      "description": "Floor Number"
    },
    {
      "enum": [
        308,
        "publicAccessAttribute"
      ],
      "description": "Public Access Attribute"
    },
    {
      "enum": [
        309,
        "outputAttribute"
      ],
      "description": "Output Attribute"
    },
    {
      "enum": [
        310,
        "inputAttribute"
      ],
      "description": "Input Attribute"
    },
    {
      "enum": [
        311,
        "length"
      ],
      "description": "Length"
    },
    {
      "enum": [
        312,
        "memoryLoad"
      ],
      "description": "Memory Load"
    },
    {
      "enum": [
        313,
        "totalPhysical"
      ],
      "description": "Total Physical"
    },
    {
      "enum": [
        314,
        "availPhysical"
      ],
      "description": "Avail Physical"
    },
    {
      "enum": [
        315,
        "totalPageFile"
      ],
      "description": "Total Page File"
    },
    {
      "enum": [
        316,
        "availPageFile"
      ],
      "description": "Avail Page File"
    },
    {
      "enum": [
        317,
        "totalVirtual"
      ],
      "description": "Total Virtual"
    },
    {
      "enum": [
        318,
        "availVirtual"
      ],
      "description": "Avail Virtual"
    },
    {
      "enum": [
        319,
        "rating"
      ],
      "description": "Rating"
    },
    {
      "enum": [
        320,
        "valueAtShedTime"
      ],
      "description": "Value-At-Shed-Time"
    },
    {
      "enum": [
        321,
        "energy"
      ],
      "description": "Energy Consumption"
    },
    {
      "enum": [
        322,
        "peak"
      ],
      "description": "Peak"
    },
    {
      "enum": [
        323,
        "peakTime"
      ],
      "description": "Peak Time"
    },
    {
      "enum": [
        324,
        "projectedPeak"
      ],
      "description": "Projected Peak"
    },
    {
      "enum": [
        325,
        "projectedPeakTime"
      ],
      "description": "Projected Peak Time"
    },
    {
      "enum": [
        326,
        "targets"
      ],
      "description": "Targets"
    },
    {
      "enum": [
        327,
        "network"
      ],
      "description": "Network"
    },
    {
      "enum": [
        328,
        "maxShedTime"
      ],
      "description": "Max Shed Time"
    },
    {
      "enum": [
        329,
        "target"
      ],
      "description": "Target"
    },
    {
      "enum": [
        330,
        "description"
      ],
      "description": "Description"
    },
    {
      "enum": [
        331,
        "minShedTime"
      ],
      "description": "Min Shed Time"
    },
    {
      "enum": [
        332,
        "shedInvokeId"
      ],
      "description": "Shed invoke id"
    },
    {
      "enum": [
        333,
        "dlShed"
      ],
      "description": "DL Shed"
    },
    {
      "enum": [
        334,
        "lrShed"
      ],
      "description": "LR Shed"
    },
    {
      "enum": [
        335,
        "remReleaseTime"
      ],
      "description": "Remaining Release Time"
    },
    {
      "enum": [
        336,
        "publicAccessWhenDisconnected"
      ],
      "description": "Public Access When Disconnected"
    },
    {
      "enum": [
        337,
        "levelNumber"
      ],
      "description": "Level Number"
    },
    {
      "enum": [
        338,
        "side"
      ],
      "description": "Side"
    },
    {
      "enum": [
        339,
        "copDestinationWhenConnected"
      ],
      "description": "COP Destination When Connected"
    },
    {
      "enum": [
        340,
        "copDestinationWhenDisconnected"
      ],
      "description": "COP Destination When Disconnected"
    },
    {
      "enum": [
        341,
        "dopDestinationWhenConnected"
      ],
      "description": "DOP Destination When Connected"
    },
    {
      "enum": [
        342,
        "dopDestinationWhenDisconnected"
      ],
      "description": "DOP Destination When Disconnected"
    },
    {
      "enum": [
        343,
        "dopSourceWhenConnected"
      ],
      "description": "DOP Source When Connected"
    },
    {
      "enum": [
        344,
        "dopSourceWhenDisconnected"
      ],
      "description": "DOP Source When Disconnected"
    },
    {
      "enum": [
        345,
        "peakIntDemand"
      ],
      "description": "Peak Interval Demand"
    },
    {
      "enum": [
        346,
        "peakIntDemandTime"
      ],
      "description": "Peak Interval Demand Time"
    },
    {
      "enum": [
        347,
        "prevShedIndex"
      ],
      "description": "Prev Shed Index"
    },
    {
      "enum": [
        348,
        "nextShedIndex"
      ],
      "description": "Next Shed Index"
    },
    {
      "enum": [
        349,
        "prevReleasableIndex"
      ],
      "description": "Prev Releasable Index"
    },
    {
      "enum": [
        350,
        "nextReleasableIndex"
      ],
      "description": "Next Releasable Index"
    },
    {
      "enum": [
        351,
        "almMsgTxt"
      ],
      "description": "Alarm Message Text"
    },
    {
      "enum": [
        352,
        "multiplier"
      ],
      "description": "Multiplier"
    },
    {
      "enum": [
        353,
        "moduloDivide"
      ],
      "description": "Modulo Divide"
    },
    {
      "enum": [
        354,
        "firstLoadIndex"
      ],
      "description": "First Load Index"
    },
    {
      "enum": [
        355,
        "lastShedIndex"
      ],
      "description": "Last Shed Index"
    },
    {
      "enum": [
        356,
        "lastRealShedIndex"
      ],
      "description": "Last Real Shed Index"
    },
    {
      "enum": [
        357,
        "networkNumber"
      ],
      "description": "Network Number"
    },
    {
      "enum": [
        358,
        "deviceInstanceLowLimit"
      ],
      "description": "Device Instance Low Limit"
    },
    {
      "enum": [
        359,
        "deviceInstanceHighLimit"
      ],
      "description": "Device Instance High Limit"
    },
    {
      "enum": [
        360,
        "udpPort"
      ],
      "description": "UDP Port"
    },
    {
      "enum": [
        361,
        "deviceObjectId"
      ],
      "description": "Device Object ID"
    },
    {
      "enum": [
        362,
        "actionToTake"
      ],
      "description": "Action To Take"
    },
    {
      "enum": [
        363,
        "condition"
      ],
      "description": "Condition"
    },
    {
      "enum": [
        364,
        "dateTime"
      ],
      "description": "Date Time"
    },
    {
      "enum": [
        365,
        "fwdSuccessful"
      ],
      "description": "Forward Successful"
    },
    {
      "enum": [
        366,
        "guid"
      ],
      "description": "Identifier"
    },
    {
      "enum": [
        367,
        "password"
      ],
      "description": "Password"
    },
    {
      "enum": [
        368,
        "recSubnetMask"
      ],
      "description": "Address-Subnet Mask"
    },
    {
      "enum": [
        369,
        "itemType"
      ],
      "description": "Item Type"
    },
    {
      "enum": [
        370,
        "childItem"
      ],
      "description": "Child Item"
    },
    {
      "enum": [
        371,
        "columnId"
      ],
      "description": "Column Id"
    },
    {
      "enum": [
        372,
        "attributeId"
      ],
      "description": "Attribute Id"
    },
    {
      "enum": [
        373,
        "attributeName"
      ],
      "description": "Attribute Name"
    },
    {
      "enum": [
        374,
        "attributeGroup"
      ],
      "description": "Attribute Group"
    },
    {
      "enum": [
        375,
        "timestamp"
      ],
      "description": "Timestamp"
    },
    {
      "enum": [
        376,
        "accumulatedValue"
      ],
      "description": "Accumulated Value"
    },
    {
      "enum": [
        377,
        "seqTable"
      ],
      "description": "Sequence Table"
    },
    {
      "enum": [
        378,
        "deviceType"
      ],
      "description": "Device Type"
    },
    {
      "enum": [
        379,
        "devicePeakEfficiency"
      ],
      "description": "Peak Efficiency"
    },
    {
      "enum": [
        380,
        "deviceRatedChwFlow"
      ],
      "description": "Rated CHW Flow"
    },
    {
      "enum": [
        381,
        "deviceRatedChFlow"
      ],
      "description": "Rated CW Flow"
    },
    {
      "enum": [
        382,
        "deviceRatedCurrent"
      ],
      "description": "Rated Current/Power"
    },
    {
      "enum": [
        383,
        "deviceRatedCapcity"
      ],
      "description": "Rated Capacity"
    },
    {
      "enum": [
        384,
        "deviceChwMinFlow"
      ],
      "description": "CHW Min Flow"
    },
    {
      "enum": [
        385,
        "deviceCwMinFlow"
      ],
      "description": "CW Min Flow"
    },
    {
      "enum": [
        386,
        "methodId"
      ],
      "description": "Method Id"
    },
    {
      "enum": [
        387,
        "majorReleaseId"
      ],
      "description": "Major Release Identifier"
    },
    {
      "enum": [
        388,
        "minorReleaseId"
      ],
      "description": "Minor Release Identifier"
    },
    {
      "enum": [
        389,
        "patchId"
      ],
      "description": "Patch Identifier"
    },
    {
      "enum": [
        390,
        "majorBuildId"
      ],
      "description": "Major Build Identifier"
    },
    {
      "enum": [
        391,
        "minorBuildId"
      ],
      "description": "Minor Build Identifier"
    },
    {
      "enum": [
        392,
        "assetName"
      ],
      "description": "Asset Name"
    },
    {
      "enum": [
        393,
        "startupPhase"
      ],
      "description": "Startup Phase"
    },
    {
      "enum": [
        394,
        "duration"
      ],
      "description": "Duration"
    },
    {
      "enum": [
        395,
        "propBand"
      ],
      "description": "Proportional Band"
    },
    {
      "enum": [
        396,
        "integralTime"
      ],
      "description": "Integral Time"
    },
    {
      "enum": [
        397,
        "saturationTime"
      ],
      "description": "Saturation Time"
    },
    {
      "enum": [
        398,
        "period"
      ],
      "description": "Period"
    },
    {
      "enum": [
        399,
        "deviceLiftSensitivity"
      ],
      "description": "Lift Sensitivity"
    },
    {
      "enum": [
        400,
        "deviceChwMaxFlow"
      ],
      "description": "CHW Max Flow"
    },
    {
      "enum": [
        401,
        "devicePeakCop"
      ],
      "description": "Peak COP"
    },
    {
      "enum": [
        402,
        "coil"
      ],
      "description": "Coil"
    },
    {
      "enum": [
        403,
        "scale"
      ],
      "description": "Scale"
    },
    {
      "enum": [
        404,
        "signed"
      ],
      "description": "Signed"
    },
    {
      "enum": [
        405,
        "preferenceIndex"
      ],
      "description": "Preference Index"
    },
    {
      "enum": [
        406,
        "offset"
      ],
      "description": "Offset"
    },
    {
      "enum": [
        407,
        "writeable"
      ],
      "description": "Writeable"
    },
    {
      "enum": [
        408,
        "designLift"
      ],
      "description": "Design Lift"
    },
    {
      "enum": [
        409,
        "userRole"
      ],
      "description": "User Role"
    },
    {
      "enum": [
        410,
        "objectCategory"
      ],
      "description": "Authorization Category"
    },
    {
      "enum": [
        411,
        "permissionLevel"
      ],
      "description": "Permission Level"
    },
    {
      "enum": [
        412,
        "objectClass"
      ],
      "description": "Object Class"
    },
    {
      "enum": [
        413,
        "userCommandId"
      ],
      "description": "User Command ID"
    },
    {
      "enum": [
        414,
        "commandMethodId"
      ],
      "description": "Command Method ID"
    },
    {
      "enum": [
        415,
        "inputReferenceStatus"
      ],
      "description": "Input Reference Status"
    },
    {
      "enum": [
        416,
        "warningReferenceStatus"
      ],
      "description": "Warning Reference Status"
    },
    {
      "enum": [
        417,
        "setpointReferenceStatus"
      ],
      "description": "Setpoint Reference Status"
    },
    {
      "enum": [
        418,
        "coolingSetpointReferenceStatus"
      ],
      "description": "Cooling Setpoint Reference Status"
    },
    {
      "enum": [
        419,
        "heatingSetpointReferenceStatus"
      ],
      "description": "Heating Setpoint Reference Status"
    },
    {
      "enum": [
        420,
        "occupancyReferenceStatus"
      ],
      "description": "Occupancy Reference Status"
    },
    {
      "enum": [
        421,
        "highAlarmLimit"
      ],
      "description": "High Alarm Limit"
    },
    {
      "enum": [
        422,
        "highWarningLimit"
      ],
      "description": "High Warning Limit"
    },
    {
      "enum": [
        423,
        "coolingSetpoint"
      ],
      "description": "Cooling Setpoint"
    },
    {
      "enum": [
        424,
        "heatingSetpoint"
      ],
      "description": "Heating Setpoint"
    },
    {
      "enum": [
        425,
        "lowWarningLimit"
      ],
      "description": "Low Warning Limit"
    },
    {
      "enum": [
        426,
        "lowAlarmLimit"
      ],
      "description": "Low Alarm Limit"
    },
    {
      "enum": [
        427,
        "dateRange"
      ],
      "description": "Date Range"
    },
    {
      "enum": [
        428,
        "weekNDay"
      ],
      "description": "Week and Day"
    },
    {
      "enum": [
        429,
        "calendarEntry"
      ],
      "description": "Calendar Entry"
    },
    {
      "enum": [
        430,
        "calendarReference"
      ],
      "description": "Calendar Reference"
    },
    {
      "enum": [
        431,
        "timeValues"
      ],
      "description": "Time Values"
    },
    {
      "enum": [
        432,
        "month"
      ],
      "description": "Month"
    },
    {
      "enum": [
        433,
        "week"
      ],
      "description": "Week"
    },
    {
      "enum": [
        434,
        "day"
      ],
      "description": "Day"
    },
    {
      "enum": [
        435,
        "hour"
      ],
      "description": "Hour"
    },
    {
      "enum": [
        436,
        "minute"
      ],
      "description": "Minute"
    },
    {
      "enum": [
        437,
        "postDelay"
      ],
      "description": "Post Delay"
    },
    {
      "enum": [
        438,
        "devidDefined"
      ],
      "description": "Device ID Defined"
    },
    {
      "enum": [
        439,
        "arrayIndxDefined"
      ],
      "description": "Array Index Defined"
    },
    {
      "enum": [
        440,
        "priorityDefined"
      ],
      "description": "Priority Defined"
    },
    {
      "enum": [
        441,
        "postDelayDefined"
      ],
      "description": "Post Delay Defined"
    },
    {
      "enum": [
        442,
        "maxPctLoad"
      ],
      "description": "Max Pct Load"
    },
    {
      "enum": [
        443,
        "minPctLoad"
      ],
      "description": "Min Pct Load"
    },
    {
      "enum": [
        444,
        "maxPctLoadCop"
      ],
      "description": "Max Pct Load COP"
    },
    {
      "enum": [
        445,
        "minPctLoadCop"
      ],
      "description": "Min Pct Load COP"
    },
    {
      "enum": [
        446,
        "stabilizeTime"
      ],
      "description": "Stabilize Time"
    },
    {
      "enum": [
        447,
        "interstageTransitionDelay"
      ],
      "description": "Interstage Transition Delay"
    },
    {
      "enum": [
        448,
        "avgValue"
      ],
      "description": "Avg Value"
    },
    {
      "enum": [
        449,
        "actualValue"
      ],
      "description": "Actual Value"
    },
    {
      "enum": [
        450,
        "calculatedValue"
      ],
      "description": "Calculated Value"
    },
    {
      "enum": [
        451,
        "sample"
      ],
      "description": "Sample"
    },
    {
      "enum": [
        452,
        "count"
      ],
      "description": "Count"
    },
    {
      "enum": [
        453,
        "refid"
      ],
      "description": "Refid"
    },
    {
      "enum": [
        454,
        "bufferHead"
      ],
      "description": "Buffer Head"
    },
    {
      "enum": [
        455,
        "sampleValue"
      ],
      "description": "Sample Value"
    },
    {
      "enum": [
        456,
        "hourValues"
      ],
      "description": "Hour Values"
    },
    {
      "enum": [
        457,
        "dayValues"
      ],
      "description": "Day Values"
    },
    {
      "enum": [
        458,
        "monthValues"
      ],
      "description": "Month Values"
    },
    {
      "enum": [
        459,
        "sampleBucket"
      ],
      "description": "Sample Bucket"
    },
    {
      "enum": [
        460,
        "bucketValues"
      ],
      "description": "Bucket Values"
    },
    {
      "enum": [
        461,
        "active"
      ],
      "description": "Active"
    },
    {
      "enum": [
        462,
        "dataSource"
      ],
      "description": "Data Source"
    },
    {
      "enum": [
        463,
        "componentId"
      ],
      "description": "Component Identifier"
    },
    {
      "enum": [
        464,
        "presenceSource"
      ],
      "description": "Presence Source"
    },
    {
      "enum": [
        465,
        "udpSendPort"
      ],
      "description": "UDP Send Port"
    },
    {
      "enum": [
        466,
        "udpRecvPort"
      ],
      "description": "UDP Receive Port"
    },
    {
      "enum": [
        467,
        "syslogServer"
      ],
      "description": "Syslog Server"
    },
    {
      "enum": [
        468,
        "auditEnabled"
      ],
      "description": "Audit Reporting Enabled"
    },
    {
      "enum": [
        469,
        "eventEnabled"
      ],
      "description": "Event Reporting Enabled"
    },
    {
      "enum": [
        470,
        "shortName"
      ],
      "description": "Short Name"
    },
    {
      "enum": [
        471,
        "searchCriteria"
      ],
      "description": "Search Criteria"
    },
    {
      "enum": [
        472,
        "equipmentPointType"
      ],
      "description": "Equipment Point Type"
    },
    {
      "enum": [
        473,
        "equipmentType"
      ],
      "description": "Equipment Type"
    },
    {
      "enum": [
        474,
        "availableAttributeId"
      ],
      "description": "Availability Attribute ID"
    },
    {
      "enum": [
        475,
        "availabilityFactors"
      ],
      "description": "Availability Factors"
    },
    {
      "enum": [
        476,
        "subcomponents"
      ],
      "description": "Subcomponents"
    },
    {
      "enum": [
        477,
        "subcomponent"
      ],
      "description": "Subcomponent"
    },
    {
      "enum": [
        478,
        "auditFilters"
      ],
      "description": "Audit Filters"
    },
    {
      "enum": [
        479,
        "trigger"
      ],
      "description": "Trigger"
    },
    {
      "enum": [
        480,
        "graphic"
      ],
      "description": "Graphic"
    },
    {
      "enum": [
        481,
        "graphicAlias"
      ],
      "description": "Graphic Alias"
    },
    {
      "enum": [
        482,
        "talkDirect"
      ],
      "description": "Talk Direct"
    },
    {
      "enum": [
        483,
        "userName"
      ],
      "description": "User Name"
    },
    {
      "enum": [
        484,
        "offline"
      ],
      "description": "Offline"
    },
    {
      "enum": [
        485,
        "activeCriticalAlarms"
      ],
      "description": "Active Critical Alarms"
    },
    {
      "enum": [
        486,
        "topLevelEquipmentModel"
      ],
      "description": "Top Level Equipment Model"
    },
    {
      "enum": [
        487,
        "viewDefVersion"
      ],
      "description": "View Definition Version"
    },
    {
      "enum": [
        488,
        "hideSchedule"
      ],
      "description": "Hide Schedule"
    },
    {
      "enum": [
        489,
        "deviceSize"
      ],
      "description": "Device Size"
    },
    {
      "enum": [
        490,
        "deviceNetworkSize"
      ],
      "description": "Device Network Size"
    },
    {
      "type": "null"
    }
  ]
}