{
  "$schema": "http://json-schema.org/schema#",
  "$id": "https://metasys-server.github.io/schemas/v1/enums/loggingTypeEnumSet.schema.json",
  "title": "loggingTypeEnumSet",
  "description": "Logging Type",
  "oneOf": [
    {
      "enum": [
        0,
        "loggingPolled"
      ],
      "description": "Polled"
    },
    {
      "enum": [
        1,
        "loggingCov"
      ],
      "description": "COV"
    },
    {
      "enum": [
        2,
        "loggingTriggered"
      ],
      "description": "Triggered"
    }
  ]
}