{
  "$schema": "http://json-schema.org/schema#",
  "$id": "https://metasys-server.github.io/schemas/v1/enums/seRtuSfControlOvr.schema.json",
  "title": "seRtuSfControlOvr",
  "description": "SE RTU SF Control OVR",
  "oneOf": [
    {
      "enum": [
        0,
        "seSfControlOff"
      ],
      "description": "Off"
    },
    {
      "enum": [
        1,
        "seSfControlMin"
      ],
      "description": "Min"
    },
    {
      "enum": [
        2,
        "seSfControlRamp"
      ],
      "description": "Ramp"
    },
    {
      "enum": [
        3,
        "seSfContorlControl"
      ],
      "description": "Control"
    },
    {
      "enum": [
        4,
        "seSfControlEsP"
      ],
      "description": "Emergency S-P Control"
    },
    {
      "enum": [
        5,
        "seSfControlEmerOff"
      ],
      "description": "Emergency Off"
    },
    {
      "enum": [
        6,
        "seSfControlHold"
      ],
      "description": "Hold"
    }
  ]
}