{
  "$schema": "http://json-schema.org/schema#",
  "$id": "https://metasys-server.github.io/schemas/v1/enums/unityXlpPowerEnumSet.schema.json",
  "title": "unityXlpPowerEnumSet",
  "description": "Unity XLP Power",
  "oneOf": [
    {
      "enum": [
        0,
        "0"
      ],
      "description": "PWR"
    },
    {
      "enum": [
        1,
        "1"
      ],
      "description": "PWR1"
    },
    {
      "enum": [
        2,
        "2"
      ],
      "description": "PWR2"
    },
    {
      "enum": [
        3,
        "3"
      ],
      "description": "PWR3"
    },
    {
      "enum": [
        4,
        "4"
      ],
      "description": "NORMAL"
    },
    {
      "enum": [
        5,
        "5"
      ],
      "description": "FIXED, PWR"
    },
    {
      "enum": [
        6,
        "6"
      ],
      "description": "FIXED, PWR1"
    },
    {
      "enum": [
        7,
        "7"
      ],
      "description": "FIXED, PWR2"
    },
    {
      "enum": [
        8,
        "8"
      ],
      "description": "FIXED, PWR3"
    },
    {
      "type": "null"
    }
  ]
}